{"dependencies":[{"name":"C:\\Users\\ADMIN\\Desktop\\handwritten-digit-recognition-canvas-draw\\package.json","includedInParent":true,"mtime":1589420220292},{"name":"C:\\Users\\ADMIN\\Desktop\\handwritten-digit-recognition-canvas-draw\\.babelrc","includedInParent":true,"mtime":1589420220287},{"name":"C:\\Users\\ADMIN\\Desktop\\handwritten-digit-recognition-canvas-draw\\node_modules\\readable-stream\\package.json","includedInParent":true,"mtime":1589420636029},{"name":"./lib/_stream_duplex.js","loc":{"line":1,"column":25}}],"generated":{"js":"module.exports = require('./lib/_stream_duplex.js');\n","map":{"mappings":[{"source":"node_modules\\readable-stream\\duplex-browser.js","original":{"line":1,"column":0},"generated":{"line":1,"column":0}},{"source":"node_modules\\readable-stream\\duplex-browser.js","original":{"line":2,"column":0},"generated":{"line":2,"column":0}}],"sources":{"node_modules\\readable-stream\\duplex-browser.js":"module.exports = require('./lib/_stream_duplex.js');\n"},"lineCount":2}},"hash":"7cba1c5fd9da5beb901b2ffc79447688","cacheData":{"env":{}}}